rtui_app/__init__.py
rtui_app/app/__init__.py
rtui_app/app/inspect.py
rtui_app/cli.py
rtui_app/event.py
rtui_app/ros/__init__.py
rtui_app/ros/client.py
rtui_app/ros/entity.py
rtui_app/ros/exception.py
rtui_app/ros/interface/__init__.py
rtui_app/ros/interface/base.py
rtui_app/ros/interface/ros1.py
rtui_app/ros/interface/ros2.py
rtui_app/screens.py
rtui_app/utility/__init__.py
rtui_app/utility/hisotry.py
rtui_app/widgets/__init__.py
rtui_app/widgets/info_panel.py
rtui_app/widgets/list_panel.py
rtui_app/widgets/type_definition.py
rtui_app-0.2.1.dist-info/LICENSE
rtui_app-0.2.1.dist-info/METADATA
rtui_app-0.2.1.dist-info/WHEEL
rtui_app-0.2.1.dist-info/entry_points.txt
rtui_app-0.2.1.dist-info/RECORD
