Metadata-Version: 2.1
Name: rtui-app
Version: 0.2.1
Summary: A TUI tool for ROS1/2
Home-page: https://github.com/eduidl/rtui
License: Apache-2.0
Author: Yuma Hiramatsu
Author-email: yuma.hiramatsu@gmail.com
Requires-Python: >=3.8,<4.0
Classifier: License :: OSI Approved :: Apache Software License
Classifier: Programming Language :: Python :: 3
Classifier: Programming Language :: Python :: 3.8
Classifier: Programming Language :: Python :: 3.9
Classifier: Programming Language :: Python :: 3.10
Classifier: Programming Language :: Python :: 3.11
Requires-Dist: PyYAML (>=6.0,<7.0)
Requires-Dist: click (>=8.1.3,<9.0.0)
Requires-Dist: netifaces (>=0.11.0,<0.12.0)
Requires-Dist: numpy (>=1.23.0,<2.0.0)
Requires-Dist: rospkg (>=1.4.0,<2.0.0)
Requires-Dist: textual (>=0.40,<0.41)
Requires-Dist: typing-extensions (>=4.3.0,<5.0.0)
Project-URL: Repository, https://github.com/eduidl/rtui
